parallel_wandb/__init__.py
parallel_wandb/example_test.py
parallel_wandb/init.py
parallel_wandb/init_test.py
parallel_wandb/log.py
parallel_wandb/log_test.py
parallel_wandb/map_and_log.py
parallel_wandb/map_and_log_test.py
parallel_wandb/py.typed
parallel_wandb/utils.py
parallel_wandb-0.0.2.dist-info/METADATA
parallel_wandb-0.0.2.dist-info/WHEEL
parallel_wandb-0.0.2.dist-info/licenses/LICENSE
parallel_wandb-0.0.2.dist-info/RECORD
