Metadata-Version: 2.4
Name: parallel_wandb
Version: 0.0.2
Summary: Add your description here
Author-email: Fabrice Normandin <fabrice.normandin@gmail.com>
License-File: LICENSE
Requires-Python: >=3.11
Requires-Dist: numpy>=2.2.5
Requires-Dist: optree>=0.15.0
Requires-Dist: wandb>=0.19.11
